monitor.py
shibasphoorthi/__init__.py
shibasphoorthi/sub.py
shibasphoorthi/sum.py
shibasphoorthi.egg-info/PKG-INFO
shibasphoorthi.egg-info/SOURCES.txt
shibasphoorthi.egg-info/dependency_links.txt
shibasphoorthi.egg-info/requires.txt
shibasphoorthi.egg-info/top_level.txt