Metadata-Version: 1.0
Name: shibasphoorthi
Version: 0.1
Summary: My Python module
Home-page: UNKNOWN
Author: UNKNOWN
Author-email: UNKNOWN
License: UNKNOWN
Platform: UNKNOWN
